heaty/__init__.py
heaty/__main__.py
heaty/gui/__init__.py
heaty/gui/about.py
heaty/gui/controller.py
heaty/gui/main_window.py
heaty/gui/auxiliary/__init__.py
heaty/gui/auxiliary/lines.py
heaty/gui/auxiliary/types.py
heaty/gui/climate_data/__init__.py
heaty/gui/climate_data/dialog.py
heaty/gui/climate_data/input_fields.py
heaty/gui/heated_space/__init__.py
heaty/gui/heated_space/dialog.py
heaty/gui/heated_space/input_fields.py
heaty/gui/heated_space/building_elements/__init__.py
heaty/gui/heated_space/building_elements/input_fields.py
heaty/gui/heated_space/building_elements/widget.py
heaty/gui/resources/__init__.py
heaty/gui/resources/about.html
heaty/gui/resources/house.ico
heaty/gui/resources/license.html
heaty/gui/resources/user_guide.pdf
heaty/gui/settings/__init__.py
heaty/gui/settings/dialog.py
heaty/gui/settings/settings.py
heaty/gui/user_input/__init__.py
heaty/gui/user_input/form.py
heaty/gui/user_input/processing.py
heaty/gui/ventilation_zone/__init__.py
heaty/gui/ventilation_zone/dialog.py
heaty/gui/ventilation_zone/input_fields.py
heaty/model/__init__.py
heaty/model/auxiliary.py
heaty/model/building.py
heaty/model/building_elements.py
heaty/model/climate_data.py
heaty/model/fileio.py
heaty/quantity/__init__.py
heaty/quantity/scalar.py
heaty/quantity/thermal_comfort_qties.py
Heaty-2020.10b2.dist-info/LICENSE
Heaty-2020.10b2.dist-info/METADATA
Heaty-2020.10b2.dist-info/WHEEL
Heaty-2020.10b2.dist-info/entry_points.txt
Heaty-2020.10b2.dist-info/top_level.txt
Heaty-2020.10b2.dist-info/RECORD
