Metadata-Version: 2.1
Name: Heaty
Version: 2020.10b2
Summary: A building heat load calculator
Home-page: https://github.com/TomLXXVI/heaty
Author: Tom Christiaens
Author-email: tom.chr@proximus.be
License: BSD v3
Keywords: building heat load calculator,EN 12831-1
Platform: Win32 (MS Windows)
Classifier: Development Status :: 4 - Beta
Classifier: Intended Audience :: End Users/Desktop
Classifier: Topic :: Scientific/Engineering
Classifier: Programming Language :: Python :: 3.8
Classifier: License :: OSI Approved :: BSD License
Classifier: Operating System :: Microsoft :: Windows :: Windows 10
Requires-Python: >=3.8
Requires-Dist: PyQt5
Requires-Dist: Pint
